{
  "parent": "minecraft:recipes/root",
  "criteria": {
    "has_flesh_mass": {
      "conditions": {
        "items": [
          {
            "items": "fleshforgemod:flesh_mass"
          }
        ]
      },
      "trigger": "minecraft:inventory_changed"
    },
    "has_the_recipe": {
      "conditions": {
        "recipe": "minecraft:biocpu_from_crafting"
      },
      "trigger": "minecraft:recipe_unlocked"
    }
  },
  "requirements": [
    [
      "has_the_recipe",
      "has_flesh_mass"
    ]
  ],
  "rewards": {
    "recipes": [
      "minecraft:biocpu_from_crafting"
    ]
  }
}